<annotation>
	<folder>train</folder>
	<filename>stop_7.jpg</filename>
	<path>C:/Users/Dmitry/PycharmProjects/gesture16/Tensorflow/workspace/training_demo/images/train/stop_7.jpg</path>
	<source>
		<database>Unknown</database>
	</source>
	<size>
		<width>1920</width>
		<height>1080</height>
		<depth>3</depth>
	</size>
	<segmented>0</segmented>
	<object>
		<name>stop</name>
		<pose>Unspecified</pose>
		<truncated>1</truncated>
		<difficult>0</difficult>
		<bndbox>
			<xmin>482</xmin>
			<ymin>560</ymin>
			<xmax>976</xmax>
			<ymax>1080</ymax>
		</bndbox>
	</object>
</annotation>